{
  "slug": "/school/pune/sant-tukaram-english-medium-school-katrajnagar-katraj",
  "url": "https://yellowslate.com/school/pune/sant-tukaram-english-medium-school-katrajnagar-katraj",
  "city": "pune",
  "name": "Sant Tukaram English Medium School - Katrajnagar,Katraj ",
  "scraped_at": "2026-04-28T15:56:47.634107",
  "html_length": 323133,
  "structured_data": [
    {
      "@context": "https://schema.org/",
      "@type": "BreadcrumbList",
      "itemListElement": [
        {
          "@type": "ListItem",
          "position": 1,
          "name": "Home",
          "item": "https://yellowslate.com/"
        },
        {
          "@type": "ListItem",
          "position": 2,
          "name": "Pune",
          "item": "https://yellowslate.com/schools/pune"
        },
        {
          "@type": "ListItem",
          "position": 3,
          "name": "Katrajnagar,Katraj",
          "item": "https://yellowslate.com/schools/pune/katrajnagar-katraj"
        },
        {
          "@type": "ListItem",
          "position": 4,
          "name": "STATE BOARD",
          "item": "https://yellowslate.com/schools/pune/katrajnagar-katraj/state-board"
        },
        {
          "@type": "ListItem",
          "position": 5,
          "name": "Sant Tukaram English Medium School",
          "item": "https://yellowslate.com/school/pune/sant-tukaram-english-medium-school-katrajnagar-katraj"
        }
      ]
    },
    {
      "@context": "https://schema.org",
      "@type": "LocalBusiness",
      "name": "Sant Tukaram English Medium School - Katrajnagar,Katraj",
      "image": "https://yellowslate.sgp1.cdn.digitaloceanspaces.com/schools/profile.png",
      "@id": "",
      "url": "https://yellowslate.com/school/pune/sant-tukaram-english-medium-school-katrajnagar-katraj",
      "telephone": "+91 9372619482",
      "address": {
        "@type": "PostalAddress",
        "Address": "411046, 47/2A/2, Pune - Bengaluru Hwy, Katrajnagar, Katraj, Pune, Maharashtra 411046, India",
        "addressLocality": "Pune",
        "addressCountry": "IN"
      },
      "geo": {
        "@type": "GeoCoordinates",
        "latitude": 18.4428272,
        "longitude": 73.8610189
      }
    },
    {
      "@context": "https://schema.org",
      "@type": "Review",
      "numberOfItems": 1,
      "itemListElement": [
        {
          "@type": "Review",
          "itemReviewed": {
            "@type": "School",
            "name": "Sant Tukaram English Medium School - Katrajnagar,Katraj",
            "address": {
              "@type": "PostalAddress",
              "streetAddress": "411046, 47/2A/2, Pune - Bengaluru Hwy, Katrajnagar, Katraj, Pune, Maharashtra 411046, India",
              "addressLocality": "Pune",
              "addressCountry": "IN"
            },
            "url": "https://yellowslate.com/pune/sant-tukaram-english-medium-school-katrajnagar-katraj-katrajnagar-katraj-reviews",
            "aggregateRating": {
              "@type": "AggregateRating",
              "ratingValue": "5.0",
              "reviewCount": "1"
            }
          },
          "author": {
            "@type": "Person",
            "name": "Suvarna Deshmukh"
          },
          "datePublished": "2023-08-08",
          "reviewRating": {
            "@type": "Rating",
            "ratingValue": "5",
            "bestRating": "5",
            "worstRating": "1"
          },
          "reviewBody": "Chate school",
          "publisher": {
            "@type": "Organization",
            "name": "Yellow Slate"
          }
        }
      ]
    }
  ],
  "instagram_posts": [],
  "instagram_posts_count": 0,
  "videos": [],
  "email_candidates": [],
  "website_urls": [
    "http://www.w3.org/2000/svg\\",
    "https://www.googletagmanager.com/gtm.js?id=GTM-5SW2S6T",
    "https://8views.com/\\",
    "https://www.clarity.ms/tag/",
    "https://www.clarity.ms/tag/syt030gya8",
    "https://twitter.com/yellow_slate\\",
    "https://connect.facebook.net/en_US/fbevents.js",
    "https://www.googletagmanager.com/gtag/js?id=G-BP84H9P9RR",
    "https://www.youtube.com/@yellowslateHyderabad\\",
    "https://www.clarity.ms/tag/\\\\\\",
    "https://yellowslate-blog.blr1.digitaloceanspaces.com/2024/02/54.jpg\\",
    "https://twitter.com/yellow_slate",
    "https://schema.org/\\\\\\",
    "https://wa.me/919513238818",
    "https://www.googletagmanager.com/gtag/js?id=AW-11054822296&amp;cx=c&amp;gtm=4e64o1h1",
    "https://www.googletagmanager.com/gtag/js?id=G-BP84H9P9RR\\",
    "https://8views.com/",
    "https://yellowslate.youcanbook.me/",
    "https://schema.org/",
    "https://www.youtube.com/@yellowslateHyderabad",
    "https://yellowslate-blog.blr1.digitaloceanspaces.com/2024/02/2-2.jpg\\",
    "https://schema.org\\\\\\",
    "https://yellowslate.sgp1.cdn.digitaloceanspaces.com/schools/profile.png\\\\\\",
    "http://www.w3.org/2000/svg",
    "https://yellowslate.sgp1.cdn.digitaloceanspaces.com/schools/profile.png",
    "https://www.googletagmanager.com/gtm.js?id=",
    "https://schema.org",
    "https://yellowslate.sgp1.cdn.digitaloceanspaces.com/schools/profile.png\\",
    "https://scripts.clarity.ms/0.8.59/clarity.js",
    "https://my.hellobar.com/c3e30b36ca904cf24930917abfa3d4cbb11aecfe.js"
  ],
  "rating": "5.0",
  "views": "594",
  "reviews_count": "1",
  "phone": "+919513238818",
  "locality": "Katrajnagar,Katraj",
  "board": "State Board\n\nCo",
  "established": null,
  "category": "Day Schools",
  "classes": "000 - 25",
  "gender": "Co-Education",
  "fees_range": null,
  "about": "Sant Tukaram English Medium School ?\nAsk a Question\nSant Tukaram English Medium School Reviews\nView All Reviews\nOverall Experience\n 0\nTeaching Excellence\n 0\nValue for Money\n 0\nCampus & Facilities\n 0\nCo-curricular Activities\n 0\nWrite a review",
  "images": [
    "https://yellowslate.sgp1.cdn.digitaloceanspaces.com/schools/profile.png",
    "https://yellowslate-blog.blr1.digitaloceanspaces.com/2024/02/2-2.jpg",
    "https://yellowslate-blog.blr1.digitaloceanspaces.com/2024/02/54.jpg",
    "https://www.facebook.com/tr?id=1737704393208569&amp;ev=PageView&amp;noscript=1",
    "https://yellowslate.com/_next/image?url=%2Fimages%2Flogo.png&amp;w=1200&amp;q=75"
  ]
}