{
  "id": "adarsh-gyan-sarovar-balika-vidyalay-ganwari-marginal-bandh",
  "name": "ADARSH GYAN SAROVAR BALIKA VIDYALAY",
  "slug": "/school/delhi/adarsh-gyan-sarovar-balika-vidyalay-ganwari-marginal-bandh",
  "city": "delhi",
  "page_number": 112,
  "position_on_page": 1,
  "address": "GANWARI MARGINAL BANDH",
  "locality": "GANWARI MARGINAL BANDH",
  "board": "CBSE",
  "medium": "English",
  "school_type": "CBSE",
  "established": "",
  "grades": "",
  "fees": {
    "min": null,
    "max": null,
    "currency": "INR",
    "period": "annually"
  },
  "fees_text": "",
  "contact": {
    "phone": "+919513238818",
    "email": "",
    "website": ""
  },
  "facilities": [],
  "admission": {
    "status": "unknown"
  },
  "rating": null,
  "reviews_count": null,
  "images": [],
  "listing_only": true,
  "listing_page": "https://yellowslate.com/schools/delhi",
  "scraped_at": "2026-04-25T19:44:18.717875"
}