{
  "slug": "/school/chennai/sri-sankara-senior-secondary-school-adyar",
  "url": "https://yellowslate.com/school/chennai/sri-sankara-senior-secondary-school-adyar",
  "city": "chennai",
  "name": "SRI SANKARA SENIOR SECONDARY SCHOOL - Adyar ",
  "scraped_at": "2026-04-28T17:29:14.437009",
  "html_length": 354668,
  "structured_data": [
    {
      "@context": "https://schema.org/",
      "@type": "BreadcrumbList",
      "itemListElement": [
        {
          "@type": "ListItem",
          "position": 1,
          "name": "Home",
          "item": "https://yellowslate.com/"
        },
        {
          "@type": "ListItem",
          "position": 2,
          "name": "Chennai",
          "item": "https://yellowslate.com/schools/chennai"
        },
        {
          "@type": "ListItem",
          "position": 3,
          "name": "Adyar",
          "item": "https://yellowslate.com/schools/chennai/adyar"
        },
        {
          "@type": "ListItem",
          "position": 4,
          "name": "SRI SANKARA SENIOR SECONDARY SCHOOL",
          "item": "https://yellowslate.com/school/chennai/sri-sankara-senior-secondary-school-adyar"
        }
      ]
    },
    {
      "@context": "https://schema.org",
      "@type": "LocalBusiness",
      "name": "SRI SANKARA SENIOR SECONDARY SCHOOL - Adyar",
      "image": "https://yellowslate.sgp1.cdn.digitaloceanspaces.com/schools/null",
      "@id": "",
      "url": "https://yellowslate.com/school/chennai/sri-sankara-senior-secondary-school-adyar",
      "telephone": "",
      "address": {
        "@type": "PostalAddress",
        "Address": null,
        "addressLocality": "Chennai",
        "addressCountry": "IN"
      },
      "geo": {
        "@type": "GeoCoordinates",
        "latitude": 13.0100267,
        "longitude": 80.2609395
      }
    },
    {
      "@context": "https://schema.org",
      "@type": "Review",
      "numberOfItems": 5,
      "itemListElement": [
        {
          "@type": "Review",
          "itemReviewed": {
            "@type": "School",
            "name": "SRI SANKARA SENIOR SECONDARY SCHOOL - Adyar",
            "address": {
              "@type": "PostalAddress",
              "streetAddress": null,
              "addressLocality": "Chennai",
              "addressCountry": "IN"
            },
            "url": "https://yellowslate.com/chennai/sri-sankara-senior-secondary-school-adyar-adyar-reviews",
            "aggregateRating": {
              "@type": "AggregateRating",
              "ratingValue": "1.8",
              "reviewCount": "5"
            }
          },
          "author": {
            "@type": "Person",
            "name": "tinto noval"
          },
          "datePublished": "2023-08-15",
          "reviewRating": {
            "@type": "Rating",
            "ratingValue": "1",
            "bestRating": "5",
            "worstRating": "1"
          },
          "reviewBody": "one of the worst school in Chennai ,one of the worst teachers is Tamil teacher Revathi and SivagamaSundari",
          "publisher": {
            "@type": "Organization",
            "name": "Yellow Slate"
          }
        },
        {
          "@type": "Review",
          "itemReviewed": {
            "@type": "School",
            "name": "SRI SANKARA SENIOR SECONDARY SCHOOL - Adyar"
          },
          "author": {
            "@type": "Person",
            "name": "Haritha"
          },
          "datePublished": "2023-06-12",
          "reviewRating": {
            "@type": "Rating",
            "ratingValue": "1",
            "bestRating": "5",
            "worstRating": "1"
          },
          "reviewBody": "Really wondering i too experienced the same  here how the management or principal  has not taken action  e against these teachers like Revathi  the tamil teacher who uses foul language towards the children, these teachers Revathi, Roopa Ramesh,  kirthi Praveen  , Malavikha , hindi teacher Raji, can check with the children whether these teachers are addicted to cell phone, and deeply involve in the cellphone during class hours , many times complained to the Principal also,. not taken any action against these because Mita Venkatesh don't want any issues she wants only salary  . No punctuality among children after bell rings also children can come before the end of the first period no discipline among children any hair style can do, no nail trimming among children scratch each other, All these thing we took these issues  many times to the Principal and vice principal Vidya lakshmi, but every thing in the deaf hear",
          "publisher": {
            "@type": "Organization",
            "name": "Yellow Slate"
          }
        },
        {
          "@type": "Review",
          "itemReviewed": {
            "@type": "School",
            "name": "SRI SANKARA SENIOR SECONDARY SCHOOL - Adyar"
          },
          "author": {
            "@type": "Person",
            "name": "Shiva Prakasam"
          },
          "datePublished": "2023-06-11",
          "reviewRating": {
            "@type": "Rating",
            "ratingValue": "1",
            "bestRating": "5",
            "worstRating": "1"
          },
          "reviewBody": "On behalf of all the  parents bringing notice to the management, many times complained about this to the Principal and vice principal no step as taken so far , the get  as a feedback in the PTA meeting  then  the paper goes in the trash , several times complained about the teacher Roopa Ramesh who is unfit to handle the 6th and 7th social  science,  just reads the book that's it any single query related about the subject unfit to clear the doubt , before allocating the respective subjects to the teachers it's the duty of the principal to interview them thoroughly whether they are eligible to handle the middle class. As a parent we know these teachers Roopa Ramesh, kèerthi Pravin,  are unfit to handle the primary class there too they read the book don't to explain the topic or clear the doubts . Principal mam pls check the teaching of English teachers like Malavikha Giridaran,   see how the teacher teaches  in the class, requesting the management to watch single time definitely the future generation English will be poor , teacher will not  show any initiative to improve the child, performance ,All these issues  supports by the principal because Mita mam gets good package  she don't disturb the teachers let them teach or not , let the teachers  sit and watch cell phone in the class doesn't matter,  Anyways Principal will not come for rounds sits inside the  fourwalls ,  for sure she don't come for rounds like other principals ,depends on vice principal who goes rarely for.  rounds and supports these sleepy teachers and gives wrong information and acts wisely to become principal .",
          "publisher": {
            "@type": "Organization",
            "name": "Yellow Slate"
          }
        },
        {
          "@type": "Review",
          "itemReviewed": {
            "@type": "School",
            "name": "SRI SANKARA SENIOR SECONDARY SCHOOL - Adyar"
          },
          "author": {
            "@type": "Person",
            "name": "ume12882 raju"
          },
          "datePublished": "2023-06-10",
          "reviewRating": {
            "@type": "Rating",
            "ratingValue": "1",
            "bestRating": "5",
            "worstRating": "1"
          },
          "reviewBody": "One of the Worst school i have experienced ,the teachers are really horrible, especially Tamil teacher Revathi she is very very worst  who doesn't treat the children in good manner and she speaks bad language in the class .Especially she is making groupism with other teachers like shivagma sundari and faced worst experience with other teachers also The principal and Vice Principal  like Vidhya Lakshmi doesn't even come for rounds and another horrible teacher i have faced i would recommend if your child  needs good education. Start thinking from now to switch off from the school...... like this teachers if the please dont make child education life spoil  in joining this school",
          "publisher": {
            "@type": "Organization",
            "name": "Yellow Slate"
          }
        },
        {
          "@type": "Review",
          "itemReviewed": {
            "@type": "School",
            "name": "SRI SANKARA SENIOR SECONDARY SCHOOL - Adyar"
          },
          "author": {
            "@type": "Person",
            "name": "Adithya Raam Sankar"
          },
          "datePublished": "2017-03-19",
          "reviewRating": {
            "@type": "Rating",
            "ratingValue": "5",
            "bestRating": "5",
            "worstRating": "1"
          },
          "reviewBody": "Excellent school..\nHas some of the best teachers in the city..\nReceived the best education that helped me even during college...",
          "publisher": {
            "@type": "Organization",
            "name": "Yellow Slate"
          }
        }
      ]
    }
  ],
  "instagram_posts": [],
  "instagram_posts_count": 0,
  "videos": [],
  "email_candidates": [],
  "website_urls": [
    "https://schema.org\\",
    "https://8views.com/\\",
    "https://www.clarity.ms/tag/",
    "https://connect.facebook.net/en_US/fbevents.js",
    "http://www.w3.org/2000/svg\\",
    "https://yellowslate.sgp1.cdn.digitaloceanspaces.com/schools/null",
    "https://schema.org/",
    "https://8views.com/",
    "https://www.googletagmanager.com/gtag/js?id=AW-11054822296&amp;cx=c&amp;gtm=4e64r0h2",
    "https://twitter.com/yellow_slate",
    "https://www.googletagmanager.com/gtm.js?id=GTM-5SW2S6T",
    "https://www.googletagmanager.com/gtm.js?id=",
    "https://www.googletagmanager.com/gtag/js?id=G-BP84H9P9RR\\",
    "https://yellowslate.youcanbook.me/",
    "https://yellowslate.sgp1.cdn.digitaloceanspaces.com/schools/thumb.png\\",
    "https://www.clarity.ms/tag/syt030gya8",
    "https://schema.org",
    "https://www.googletagmanager.com/gtag/js?id=G-BP84H9P9RR",
    "http://www.w3.org/2000/svg",
    "https://yellowslate-blog.blr1.digitaloceanspaces.com/2024/02/3-6.jpg\\",
    "https://yellowslate.sgp1.cdn.digitaloceanspaces.com/schools/null\\\\\\",
    "https://www.youtube.com/@yellowslateHyderabad\\",
    "https://my.hellobar.com/c3e30b36ca904cf24930917abfa3d4cbb11aecfe.js",
    "https://yellowslate.sgp1.cdn.digitaloceanspaces.com/schools/16047449646069502265fa67704269571604744964.jpg\\",
    "https://www.clarity.ms/tag/\\\\\\",
    "https://yellowslate.sgp1.cdn.digitaloceanspaces.com/schools/15866996137142243205e931d5d577851586699613.png\\",
    "https://twitter.com/yellow_slate\\",
    "https://wa.me/919513238818",
    "https://www.youtube.com/@yellowslateHyderabad",
    "https://schema.org/\\\\\\",
    "https://schema.org\\\\\\",
    "https://scripts.clarity.ms/0.8.59/clarity.js",
    "https://yellowslate-blog.blr1.digitaloceanspaces.com/2024/01/29-2.jpg\\"
  ],
  "rating": "1.8",
  "views": "758",
  "reviews_count": "5",
  "phone": "+919513238818",
  "locality": "Adyar",
  "board": "CBSE, ICSE, IB, or Cambridge",
  "established": null,
  "category": null,
  "classes": "200 - 59",
  "gender": null,
  "fees_range": null,
  "about": "SRI SANKARA SENIOR SECONDARY SCHOOL ?\nAsk a Question\nSRI SANKARA SENIOR SECONDARY SCHOOL Reviews\nView All Reviews\nOverall Experience\n 0\nTeaching Excellence\n 0\nValue for Money\n 0\nCampus & Facilities\n 0\nCo-curricular Activities\n 0\nWrite a review",
  "images": [
    "https://yellowslate.sgp1.cdn.digitaloceanspaces.com/schools/thumb.png",
    "https://yellowslate.sgp1.cdn.digitaloceanspaces.com/schools/16047449646069502265fa67704269571604744964.jpg",
    "https://yellowslate-blog.blr1.digitaloceanspaces.com/2024/01/29-2.jpg",
    "https://yellowslate.sgp1.cdn.digitaloceanspaces.com/schools/null",
    "https://yellowslate.com/_next/image?url=%2Fimages%2Flogo.png&amp;w=1200&amp;q=75",
    "https://yellowslate-blog.blr1.digitaloceanspaces.com/2024/02/3-6.jpg",
    "https://www.facebook.com/tr?id=1737704393208569&amp;ev=PageView&amp;noscript=1"
  ]
}