{
  "id": "reserve-bank-staff-quarters-school-besant-nagar",
  "name": "Reserve Bank Staff Quarters School",
  "slug": "/school/chennai/reserve-bank-staff-quarters-school-besant-nagar",
  "city": "chennai",
  "page_number": 13,
  "position_on_page": 5,
  "address": "Besant Nagar",
  "locality": "Besant Nagar",
  "board": "CBSE",
  "medium": "English",
  "school_type": "CBSE",
  "established": "",
  "grades": "",
  "fees": {
    "min": null,
    "max": null,
    "currency": "INR",
    "period": "annually"
  },
  "fees_text": "",
  "contact": {
    "phone": "+919513238818",
    "email": "",
    "website": ""
  },
  "facilities": [],
  "admission": {
    "status": "unknown"
  },
  "rating": null,
  "reviews_count": null,
  "images": [],
  "listing_only": true,
  "listing_page": "https://yellowslate.com/schools/chennai",
  "scraped_at": "2026-04-25T09:40:02.402902"
}