{
  "slug": "/school/chennai/amelio-abiramapuram",
  "url": "https://yellowslate.com/school/chennai/amelio-abiramapuram",
  "city": "chennai",
  "name": "Amelio - Abiramapuram ",
  "scraped_at": "2026-04-28T18:38:40.396466",
  "html_length": 348672,
  "structured_data": [
    {
      "@context": "https://schema.org/",
      "@type": "BreadcrumbList",
      "itemListElement": [
        {
          "@type": "ListItem",
          "position": 1,
          "name": "Home",
          "item": "https://yellowslate.com/"
        },
        {
          "@type": "ListItem",
          "position": 2,
          "name": "Chennai",
          "item": "https://yellowslate.com/schools/chennai"
        },
        {
          "@type": "ListItem",
          "position": 3,
          "name": "Abiramapuram",
          "item": "https://yellowslate.com/schools/chennai/abiramapuram"
        },
        {
          "@type": "ListItem",
          "position": 4,
          "name": "OTHER BOARDS",
          "item": "https://yellowslate.com/schools/chennai/abiramapuram/other-boards"
        },
        {
          "@type": "ListItem",
          "position": 5,
          "name": "Amelio",
          "item": "https://yellowslate.com/school/chennai/amelio-abiramapuram"
        }
      ]
    },
    {
      "@context": "https://schema.org",
      "@type": "LocalBusiness",
      "name": "Amelio - Abiramapuram",
      "image": "https://yellowslate.sgp1.cdn.digitaloceanspaces.com/schools/16019074071105171385f7b2acfda64f1601907408.PNG",
      "@id": "",
      "url": "https://yellowslate.com/school/chennai/amelio-abiramapuram",
      "telephone": "+919176024000",
      "address": {
        "@type": "PostalAddress",
        "Address": "VTN Towers Plot no: 12, 13,14 Egattur Village, Siruseri Kanchipuram District, Chengalpet, Taluk, Chennai, Tamil Nadu 603103",
        "addressLocality": "Chennai",
        "addressCountry": "IN"
      },
      "geo": {
        "@type": "GeoCoordinates",
        "latitude": 12.8307085,
        "longitude": 80.2292456
      }
    }
  ],
  "instagram_posts": [],
  "instagram_posts_count": 0,
  "videos": [],
  "email_candidates": [],
  "website_urls": [
    "https://scripts.clarity.ms/0.8.59/clarity.js",
    "https://8views.com/",
    "https://schema.org/\\\\\\",
    "https://schema.org\\\\\\",
    "https://yellowslate.sgp1.cdn.digitaloceanspaces.com/schools/16019074071105171385f7b2acfda64f1601907408.PNG",
    "https://yellowslate.sgp1.cdn.digitaloceanspaces.com/schools/15911578848927443225ed7247c0dfcd1591157884.PNG\\",
    "https://my.hellobar.com/c3e30b36ca904cf24930917abfa3d4cbb11aecfe.js",
    "https://yellowslate.youcanbook.me/",
    "https://www.youtube.com/@yellowslateHyderabad",
    "https://schema.org/",
    "https://yellowslate.sgp1.cdn.digitaloceanspaces.com/schools/15972302976032667395f33ccd9c9b2f1597230298.PNG\\",
    "https://schema.org",
    "https://www.googletagmanager.com/gtag/js?id=G-BP84H9P9RR",
    "https://www.googletagmanager.com/gtag/js?id=AW-11054822296&amp;cx=c&amp;gtm=4e64o1",
    "https://yellowslate-blog.blr1.digitaloceanspaces.com/2024/01/29-2.jpg\\",
    "https://www.googletagmanager.com/gtm.js?id=GTM-5SW2S6T",
    "https://www.clarity.ms/tag/\\\\\\",
    "https://wa.me/919513238818",
    "https://yellowslate.sgp1.cdn.digitaloceanspaces.com/schools/16019074071105171385f7b2acfda64f1601907408.PNG\\",
    "https://twitter.com/yellow_slate\\",
    "https://yellowslate-blog.blr1.digitaloceanspaces.com/2024/02/3-6.jpg\\",
    "https://connect.facebook.net/en_US/fbevents.js",
    "http://www.w3.org/2000/svg",
    "https://yellowslate.sgp1.cdn.digitaloceanspaces.com/schools/15859900816746371455e8849c1c2f501585990082.jpg\\",
    "https://yellowslate.sgp1.cdn.digitaloceanspaces.com/team/160190801513069556375f7b2d2f76c751601908015.jpg\\",
    "https://www.clarity.ms/tag/syt030gya8",
    "http://www.w3.org/2000/svg\\",
    "https://yellowslate.sgp1.cdn.digitaloceanspaces.com/schools/16019074071105171385f7b2acfda64f1601907408.PNG\\\\\\",
    "https://www.youtube.com/@yellowslateHyderabad\\",
    "https://twitter.com/yellow_slate",
    "https://yellowslate.sgp1.cdn.digitaloceanspaces.com/schools/16019074071105171385f7b2acfda64f1601907408.PNG&quot;);",
    "https://yellowslate.sgp1.cdn.digitaloceanspaces.com/sports/Yoga.png\\",
    "https://www.googletagmanager.com/gtm.js?id=",
    "https://8views.com/\\",
    "https://www.googletagmanager.com/gtag/js?id=G-BP84H9P9RR\\",
    "https://www.clarity.ms/tag/"
  ],
  "rating": "0",
  "views": "648",
  "reviews_count": "0",
  "phone": "+919513238818",
  "locality": "Abiramapuram",
  "board": "Other Boards\n\nCo",
  "established": "2008",
  "category": "Play Schools",
  "classes": "2026-27",
  "gender": "Co-Education",
  "fees_range": null,
  "about": "Gallery\nLocation\nFaculty\nSports\nReviews",
  "images": [
    "https://yellowslate.sgp1.cdn.digitaloceanspaces.com/schools/16019074071105171385f7b2acfda64f1601907408.PNG",
    "https://yellowslate.com/_next/image?url=%2Fimages%2Flogo.png&amp;w=1200&amp;q=75",
    "https://yellowslate.sgp1.cdn.digitaloceanspaces.com/gallery/160190741819587912125f7b2ada7a3871601907419.PNG",
    "https://yellowslate.sgp1.cdn.digitaloceanspaces.com/schools/15972302976032667395f33ccd9c9b2f1597230298.PNG",
    "https://yellowslate.sgp1.cdn.digitaloceanspaces.com/schools/15911578848927443225ed7247c0dfcd1591157884.PNG",
    "https://yellowslate-blog.blr1.digitaloceanspaces.com/2024/02/3-6.jpg",
    "https://yellowslate.sgp1.cdn.digitaloceanspaces.com/sports/Yoga.png",
    "https://yellowslate.sgp1.cdn.digitaloceanspaces.com/gallery/16019074175767294875f7b2ad94a6131601907417.PNG",
    "https://yellowslate.sgp1.cdn.digitaloceanspaces.com/gallery/16019074164500621585f7b2ad8ed2391601907417.png",
    "https://yellowslate.sgp1.cdn.digitaloceanspaces.com/gallery/160190741812043165965f7b2ada8185c1601907419.PNG",
    "https://yellowslate-blog.blr1.digitaloceanspaces.com/2024/01/29-2.jpg",
    "https://www.facebook.com/tr?id=1737704393208569&amp;ev=PageView&amp;noscript=1",
    "https://yellowslate.sgp1.cdn.digitaloceanspaces.com/team/160190801513069556375f7b2d2f76c751601908015.jpg"
  ]
}