{
  "breadcrumbs": [
    {
      "position": 1,
      "name": "Home",
      "url": "https://yellowslate.com/"
    },
    {
      "position": 2,
      "name": "Coimbatore",
      "url": "https://yellowslate.com/schools/coimbatore"
    },
    {
      "position": 3,
      "name": "Velliangiri Foothills",
      "url": "https://yellowslate.com/schools/coimbatore/velliangiri-foothills"
    },
    {
      "position": 4,
      "name": "ICSE",
      "url": "https://yellowslate.com/schools/coimbatore/velliangiri-foothills/icse"
    },
    {
      "position": 5,
      "name": "Isha Home School",
      "url": "https://yellowslate.com/school/coimbatore/isha-home-school-velliangiri-foothills"
    }
  ],
  "local_business": {
    "name": "Isha Home School - Velliangiri Foothills",
    "image": "https://yellowslate.sgp1.cdn.digitaloceanspaces.com/schools/profile.png",
    "url": "https://yellowslate.com/school/coimbatore/isha-home-school-velliangiri-foothills",
    "telephone": "+91 422 251 5444",
    "address": {
      "@type": "PostalAddress",
      "Address": "Velliangiri Foothills, Ishana Vihar Post, Coimbatore, Tamil Nadu",
      "addressLocality": "Coimbatore",
      "addressCountry": "IN"
    },
    "geo": {
      "@type": "GeoCoordinates",
      "latitude": 11.02145,
      "longitude": 76.96091
    }
  },
  "reviews": null,
  "url": "https://yellowslate.com/school/coimbatore/isha-home-school-velliangiri-foothills",
  "scraped_at": "2026-04-25T22:52:27.999483"
}