{
  "id": "sri-prarthana-school-kr-puram",
  "name": "Sri Prarthana School",
  "slug": "/school/bengaluru/sri-prarthana-school-kr-puram",
  "city": "bengaluru",
  "page_number": 16,
  "position_on_page": 5,
  "address": "KR Puram",
  "locality": "KR Puram",
  "board": "CBSE",
  "medium": "English",
  "school_type": "CBSE",
  "established": "",
  "grades": "",
  "fees": {
    "min": null,
    "max": null,
    "currency": "INR",
    "period": "annually"
  },
  "fees_text": "",
  "contact": {
    "phone": "+919513238818",
    "email": "",
    "website": ""
  },
  "facilities": [],
  "admission": {
    "status": "unknown"
  },
  "rating": null,
  "reviews_count": null,
  "images": [],
  "listing_only": true,
  "listing_page": "https://yellowslate.com/schools/bengaluru",
  "scraped_at": "2026-04-25T01:16:17.951158"
}