{
  "slug": "/school/chennai/kanchana-paati-semmancheri",
  "url": "https://yellowslate.com/school/chennai/kanchana-paati-semmancheri",
  "city": "chennai",
  "name": "Kanchana Paati - Semmancheri ",
  "scraped_at": "2026-04-28T17:31:39.298262",
  "html_length": 347876,
  "structured_data": [
    {
      "@context": "https://schema.org/",
      "@type": "BreadcrumbList",
      "itemListElement": [
        {
          "@type": "ListItem",
          "position": 1,
          "name": "Home",
          "item": "https://yellowslate.com/"
        },
        {
          "@type": "ListItem",
          "position": 2,
          "name": "Chennai",
          "item": "https://yellowslate.com/schools/chennai"
        },
        {
          "@type": "ListItem",
          "position": 3,
          "name": "Semmancheri",
          "item": "https://yellowslate.com/schools/chennai/semmancheri"
        },
        {
          "@type": "ListItem",
          "position": 4,
          "name": "OTHER BOARDS",
          "item": "https://yellowslate.com/schools/chennai/semmancheri/other-boards"
        },
        {
          "@type": "ListItem",
          "position": 5,
          "name": "Kanchana Paati",
          "item": "https://yellowslate.com/school/chennai/kanchana-paati-semmancheri"
        }
      ]
    },
    {
      "@context": "https://schema.org",
      "@type": "LocalBusiness",
      "name": "Kanchana Paati - Semmancheri",
      "image": "https://yellowslate.sgp1.cdn.digitaloceanspaces.com/schools/160311060012403462725f8d86c86be5d1603110600.PNG",
      "@id": "",
      "url": "https://yellowslate.com/school/chennai/kanchana-paati-semmancheri",
      "telephone": "+919790930970",
      "address": {
        "@type": "PostalAddress",
        "Address": "DLF Garden City Door No 011, first floor, Tower 27 Semmancheri, Chennai, Tamil Nadu 600119",
        "addressLocality": "Chennai",
        "addressCountry": "IN"
      },
      "geo": {
        "@type": "GeoCoordinates",
        "latitude": 12.8746151,
        "longitude": 80.2061792
      }
    }
  ],
  "instagram_posts": [],
  "instagram_posts_count": 0,
  "videos": [],
  "email_candidates": [],
  "website_urls": [
    "https://yellowslate.sgp1.cdn.digitaloceanspaces.com/schools/160311060012403462725f8d86c86be5d1603110600.PNG\\",
    "https://8views.com/\\",
    "https://connect.facebook.net/en_US/fbevents.js",
    "https://www.clarity.ms/tag/",
    "http://www.w3.org/2000/svg\\",
    "https://schema.org/",
    "https://8views.com/",
    "https://www.googletagmanager.com/gtag/js?id=AW-11054822296&amp;cx=c&amp;gtm=4e64r0h2",
    "https://twitter.com/yellow_slate",
    "https://www.googletagmanager.com/gtm.js?id=GTM-5SW2S6T",
    "https://www.googletagmanager.com/gtm.js?id=",
    "https://yellowslate.sgp1.cdn.digitaloceanspaces.com/schools/160311060012403462725f8d86c86be5d1603110600.PNG\\\\\\",
    "https://yellowslate.sgp1.cdn.digitaloceanspaces.com/schools/160311060012403462725f8d86c86be5d1603110600.PNG",
    "https://www.googletagmanager.com/gtag/js?id=G-BP84H9P9RR\\",
    "https://yellowslate.youcanbook.me/",
    "https://yellowslate.sgp1.cdn.digitaloceanspaces.com/schools/thumb.png\\",
    "https://www.clarity.ms/tag/syt030gya8",
    "https://schema.org",
    "https://www.googletagmanager.com/gtag/js?id=G-BP84H9P9RR",
    "http://www.w3.org/2000/svg",
    "https://yellowslate-blog.blr1.digitaloceanspaces.com/2024/02/3-6.jpg\\",
    "https://yellowslate.sgp1.cdn.digitaloceanspaces.com/schools/159714791613160079285f328b0c360661597147916.PNG\\",
    "https://www.youtube.com/@yellowslateHyderabad\\",
    "https://my.hellobar.com/c3e30b36ca904cf24930917abfa3d4cbb11aecfe.js",
    "https://www.clarity.ms/tag/\\\\\\",
    "https://twitter.com/yellow_slate\\",
    "https://wa.me/919513238818",
    "https://yellowslate.sgp1.cdn.digitaloceanspaces.com/sports/Yoga.png\\",
    "https://www.youtube.com/@yellowslateHyderabad",
    "https://schema.org/\\\\\\",
    "https://schema.org\\\\\\",
    "https://scripts.clarity.ms/0.8.59/clarity.js",
    "https://yellowslate.sgp1.cdn.digitaloceanspaces.com/schools/16030093044407157435f8bfb181c9651603009304.PNG\\",
    "https://yellowslate-blog.blr1.digitaloceanspaces.com/2024/01/29-2.jpg\\"
  ],
  "rating": "0",
  "views": "669",
  "reviews_count": "0",
  "phone": "+919513238818",
  "locality": "Semmancheri",
  "board": "Other Boards\n\nCo",
  "established": "2006",
  "category": "Play Schools",
  "classes": "000 - 35",
  "gender": "Co-Education",
  "fees_range": null,
  "about": "Gallery\nLocation\nSports\nReviews",
  "images": [
    "https://yellowslate.sgp1.cdn.digitaloceanspaces.com/gallery/16031106081852832125f8d86d0ba68a1603110609.PNG",
    "https://yellowslate.sgp1.cdn.digitaloceanspaces.com/schools/thumb.png",
    "https://yellowslate.sgp1.cdn.digitaloceanspaces.com/sports/Yoga.png",
    "https://yellowslate-blog.blr1.digitaloceanspaces.com/2024/01/29-2.jpg",
    "https://yellowslate.sgp1.cdn.digitaloceanspaces.com/gallery/16031106084675341405f8d86d0c25ba1603110609.PNG",
    "https://yellowslate.sgp1.cdn.digitaloceanspaces.com/schools/160311060012403462725f8d86c86be5d1603110600.PNG",
    "https://yellowslate.com/_next/image?url=%2Fimages%2Flogo.png&amp;w=1200&amp;q=75",
    "https://yellowslate-blog.blr1.digitaloceanspaces.com/2024/02/3-6.jpg",
    "https://yellowslate.sgp1.cdn.digitaloceanspaces.com/gallery/16031106086483514655f8d86d0ce01f1603110609.PNG",
    "https://yellowslate.sgp1.cdn.digitaloceanspaces.com/schools/16030093044407157435f8bfb181c9651603009304.PNG",
    "https://www.facebook.com/tr?id=1737704393208569&amp;ev=PageView&amp;noscript=1",
    "https://yellowslate.sgp1.cdn.digitaloceanspaces.com/gallery/16031106081854935635f8d86d0cbe541603110609.PNG"
  ]
}